pigra/__init__.py
pigra/__main__.py
pigra/constants.py
pigra/parser.py
pigra/sounding.py
pigra/utils.py
pigra-1.0.2.dist-info/METADATA
pigra-1.0.2.dist-info/WHEEL
pigra-1.0.2.dist-info/top_level.txt
pigra-1.0.2.dist-info/RECORD
