Metadata-Version: 2.1
Name: pigra
Version: 1.0.2
Summary: A Python IGRA v2 parser
Home-page: https://github.com/pixel-ports/pigra
Author: Fabien Battello
Author-email: fabien.battello@orange.com
License: Apache 2.0
Platform: UNKNOWN
Classifier: License :: OSI Approved :: Apache Software License
Classifier: Operating System :: OS Independent
Classifier: Development Status :: 5 - Production/Stable
Classifier: Intended Audience :: Developers
Classifier: Programming Language :: Python :: 3
Classifier: Programming Language :: Python :: 3.8
Requires-Python: >=3.8
